setup.py
quickapi/__init__.py
quickapi.egg-info/PKG-INFO
quickapi.egg-info/SOURCES.txt
quickapi.egg-info/dependency_links.txt
quickapi.egg-info/requires.txt
quickapi.egg-info/top_level.txt