Metadata-Version: 1.1
Name: quickapi
Version: 0.5
Summary: Just quick APIs
Home-page: http://yeisoncardona.com/
Author: Yeison Cardona
Author-email: yeisoneng@gmail.com
License: BSD License
Download-URL: https://bitbucket.org/yeisoneng/python-quickapi/downloads
Platform: UNKNOWN
Classifier: Environment :: Web Environment
